djangocms_blog_agenda/__init__.py
djangocms_blog_agenda/admin.py
djangocms_blog_agenda/apps.py
djangocms_blog_agenda/cms_plugins.py
djangocms_blog_agenda/misc.py
djangocms_blog_agenda/models.py
djangocms_blog_agenda/patched_urls.py
djangocms_blog_agenda/signals.py
djangocms_blog_agenda/utils.py
djangocms_blog_agenda/views.py
djangocms_blog_agenda/conf/__init__.py
djangocms_blog_agenda/conf/settings.py
djangocms_blog_agenda/locale/fr/LC_MESSAGES/django.mo
djangocms_blog_agenda/locale/fr/LC_MESSAGES/django.po
djangocms_blog_agenda/migrations/0001_initial.py
djangocms_blog_agenda/migrations/0002_auto_20230330_1359.py
djangocms_blog_agenda/migrations/0003_upcomingeventsplugin.py
djangocms_blog_agenda/migrations/0004_pasteventsplugin.py
djangocms_blog_agenda/migrations/0005_latestpostsplugin.py
djangocms_blog_agenda/migrations/0006_rename.py
djangocms_blog_agenda/migrations/0007_auto_20241007_1222.py
djangocms_blog_agenda/migrations/0008_auto_20241011_1615.py
djangocms_blog_agenda/migrations/0009_postextension_is_pinned_and_more.py
djangocms_blog_agenda/migrations/__init__.py
djangocms_blog_agenda/templates/djangocms_blog_agenda/blog_meta.html
djangocms_blog_agenda/templates/djangocms_blog_agenda/post_detail.html
djangocms_blog_agenda/templates/djangocms_blog_agenda/post_item.html
djangocms_blog_agenda/templates/djangocms_blog_agenda/post_list.html
djangocms_blog_agenda/templates/djangocms_blog_agenda/includes/item_with_counter.html
djangocms_blog_agenda/templates/djangocms_blog_agenda/plugins/archive.html
djangocms_blog_agenda/templates/djangocms_blog_agenda/plugins/categories.html
djangocms_blog_agenda/templates/djangocms_blog_agenda/plugins/tags.html
djangocms_blog_agenda/tests/__init__.py
djangocms_blog_agenda/tests/conftest.py
djangocms_blog_agenda/tests/settings.py
djangocms_blog_agenda/tests/test_views.py
djangocms_blog_agenda-0.13.1.dist-info/licenses/AUTHORS.md
djangocms_blog_agenda-0.13.1.dist-info/licenses/LICENSE
djangocms_blog_agenda-0.13.1.dist-info/METADATA
djangocms_blog_agenda-0.13.1.dist-info/WHEEL
djangocms_blog_agenda-0.13.1.dist-info/top_level.txt
djangocms_blog_agenda-0.13.1.dist-info/RECORD
